brion/libBrainPythonHelpers.so.3.3.10
brion/libBrion.so
brion/libBrain.so
brion/libBrain.so.3.3.10
brion/libBrain.so.3.3
brion/libsonata.so.0.1.20
brion/__init__.py
brion/libBrion.so.3.3.10
brion/libBrainPythonHelpers.so
brion/libsonata.so
brion/libBrainPythonHelpers.so.3.3
brion/libBrion.so.3.3
brion/libmorphio.so
brion/_brion.so
brion/libsonata.so.0.1
brion/neuron/__init__.py
brion-3.3.10.dist-info/LICENSE.txt
brion-3.3.10.dist-info/AUTHORS.txt
brion-3.3.10.dist-info/METADATA
brion-3.3.10.dist-info/RECORD
brion-3.3.10.dist-info/top_level.txt
brion-3.3.10.dist-info/WHEEL
brion.libs/libboost_iostreams-2d90fd39.so.1.82.0
brion.libs/libboost_atomic-34eda58a.so.1.82.0
brion.libs/libBrain-6b91aee2.so.3.3.10
brion.libs/libboost_filesystem-f4168529.so.1.82.0
brion.libs/libboost_python311-e353f64e.so.1.82.0
brion.libs/libBrion-1531804a.so.3.3.10
brion.libs/libsonata-e20e41a2.so.0.1.20
brion.libs/libsz-fcfb8163.so.2.0.1
brion.libs/libbz2-a273e504.so.1.0.6
brion.libs/libboost_regex-2d234852.so.1.82.0
brion.libs/libhdf5-9f5f0521.so.200.1.0
brion.libs/libmorphio-228d2d6e.so
brion.libs/liblzma-004595ca.so.5.2.2
brion.libs/libpython3-72114d11.11.so.1.0
brion.libs/libaec-dda3378b.so.0.0.10
brion.libs/libBrainPythonHelpers-6135b83a.so.3.3.10
