Metadata-Version: 2.1
Name: brion
Version: 3.3.10
Summary: BlueBrain I/O Library
Home-page: https://github.com/BlueBrain/Brion
Author: Blue Brain Project, EPFL
License: LGPLv3
Classifier: License :: OSI Approved :: GNU Lesser General Public License v3 (LGPLv3)
License-File: LICENSE.txt
License-File: AUTHORS.txt
Requires-Dist: numpy (>=1.19.5)
Provides-Extra: docs
Requires-Dist: sphinx-bluebrain-theme ; extra == 'docs'
